javadpackage-0.2.dist-info/METADATA
javadpackage-0.2.dist-info/RECORD
javadpackage-0.2.dist-info/WHEEL
javadpackage-0.2.dist-info/entry_points.txt
javadpackage-0.2.dist-info/top_level.txt
mypackage/__init__.py
mypackage/demo.py
mypackage/subpackage/__init__.py
mypackage/subpackage/subdemo.py
