Metadata-Version: 2.1
Name: javadpackage
Version: 0.2
Summary: this is my first python package - version 2
Home-page: http://javadmko.ir
Author: javad mokhtari
Author-email: javadmokhtari@outlook.com
License: UNKNOWN
Keywords: sample python package
Platform: UNKNOWN
